{
  "menu": {
    "languages": {
      "english": "English",
      "slovak": "Slovak",
      "czech": "Czech"
    },
    "layerView": "Layering tool",
    "areaView": "Area editor tool",
    "pageName": "Envilab",
    "views": "Views",
    "settings": "Settings"
  },
  "layerViewSidebar": {
    "tabs": {
      "layerTab": "Layers",
      "areaTab": "Areas"
    },
    "areaList": {
      "noAreas": "There are no areas to display. Please select your favorite areas in settings.",
      "confirmDeleteMessage": "Do you really want to delete the area",
      "confirmDeleteYes": "Yes, delete",
      "confirmDeleteNo": "No, cancel"
    },
    "layerList": {
      "noLayers": "There are no layers to display. Please select your favorite layers in settings."
    },
    "layerEdit": {
      "opacity": "Opacity",
      "saveBtn": "Save",
      "snackbarTextSuccess": "Changes were successfully saved!"
    },
    "layerInfo": {
      "name": "Layer name",
      "type": "Layer type",
      "projection": "Layer projection",
      "description": "Layer description"
    },
    "layersDetail": {
      "dialogTitle": "Detailed information",
      "noDetail": "No detailed information available"
    }
  },
  "selectViewSidebar": {
    "title": "New area",
    "selectedPoints": "Selected points",
    "areaName": "Area name",
    "save": "Save",
    "tooltipCoords": "Tooltip coordinates",
    "addPoint": "New point"
  },
  "settings": {
    "tabs": {
      "layers": "Layers",
      "areas": "Areas"
    },
    "layers": {
      "title": "Layers settings",
      "annotation": "Select your favorite layers, which are going to be displayed in the side bar in the Layers' view"
    },
    "areas": {
      "title": "Areas settings",
      "annotation": "Select your favorite area, which are going to be displayed in the side bar in the Areas' view"
    },
    "save": "Save changes",
    "reset": "Reset changes",
    "snackbarText": "Changes were saved!"
  },
  "selectView": {
    "title": "Area editor",
    "subtitle": "Please choose the interaction type below and draw the area directly on the map or use the import button.",
    "importBtn": "Import area",
    "saveBtn": "Save area",
    "drawOptionsLabel": "Interaction type",
    "drawOptions": {
      "point": "Point",
      "lineString": "Line string",
      "polygon": "Polygon",
      "circle": "Circle"
    },
    "saveNewAreaPopup": {
      "title": "Save New Area",
      "content": "To create a new area, please enter the area name and click Save",
      "fieldLabel": "Area name",
      "cancelBtnLabel": "Cancel",
      "saveBtnLabel": "Save",
      "requiredFieldMsg": "This field is required!"
    }
  },
  "errorWindow": {
    "errorMessage": "Something went wrong! We are very sorry, please try again later or contact your administrator."
  }
}
